n97fit/__init__.py
n97fit/__main__.py
n97fit/n97fit.py
n97fit/date/__init__.py
n97fit/date/cday.py
n97fit/date/ijmapping.py
n97fit/harmonics/__init__.py
n97fit/harmonics/fourier.py
n97fit/harmonics/frcoef.py
n97fit/harmonics/harmonic.py
n97fit/harmonics/invmat.py
n97fit/harmonics/smooth.py
n97fit/io/__init__.py
n97fit/io/logging.py
n97fit/io/read_n97format.py
n97fit/io/write_fixedformat.py
n97fit/misc/__init__.py
n97fit/misc/matching.py
n97fit/misc/reviseflag.py
n97fit-1.0.2.dist-info/AUTHORS
n97fit-1.0.2.dist-info/LICENSE
n97fit-1.0.2.dist-info/METADATA
n97fit-1.0.2.dist-info/WHEEL
n97fit-1.0.2.dist-info/entry_points.txt
n97fit-1.0.2.dist-info/top_level.txt
n97fit-1.0.2.dist-info/RECORD
