Metadata-Version: 2.1
Name: n97fit
Version: 1.0.2
Summary: This is a program of data selection and curve fitting by a digital filtering technique including Reinsch-type cubic spline, Fourier harmonics and linear interpolation. It is to derive the fitted curve to the observed data ( CO2, d13C,..), as well as to separate the seasonal, short- and long-term variations from the data. 
Author: Takakiyo Nakazawa
Maintainer-email: Hisashi Yashio <yashiro.hisashi@nies.go.jp>
License: Copyright (c) 1991-2024, n97fit developers
Classifier: Development Status :: 4 - Beta
Classifier: License :: OSI Approved :: BSD License
Classifier: Operating System :: OS Independent
Classifier: Programming Language :: Python :: 3
Classifier: Programming Language :: Python :: 3.8
Classifier: Programming Language :: Python :: 3.9
Classifier: Programming Language :: Python :: 3.10
Classifier: Programming Language :: Python :: 3.11
Classifier: Programming Language :: Python :: 3.12
Classifier: Topic :: Scientific/Engineering :: Atmospheric Science
Requires-Python: >=3.8
License-File: LICENSE
License-File: AUTHORS
Requires-Dist: numpy
Requires-Dist: scipy >=1.10
Requires-Dist: pandas <3,>=2.0
Provides-Extra: dev
Requires-Dist: build ; extra == 'dev'
